pythonisl/__init__.py
pythonisl/backends.py
pythonisl/core.py
pythonisl/urls.py
pythonisl/views.py
python_isl-1.5.dist-info/LICENSE
python_isl-1.5.dist-info/METADATA
python_isl-1.5.dist-info/WHEEL
python_isl-1.5.dist-info/top_level.txt
python_isl-1.5.dist-info/RECORD
