Metadata-Version: 2.1
Name: python-isl
Version: 1.5
Summary: A python package to wrap the islapi.
Home-page: https://github.com/istrategylabs/python-isl
Author: Joseph Solomon
Author-email: josephs@isl.co
License: MIT
Keywords: python isl api
Platform: UNKNOWN
Classifier: Topic :: Utilities
Classifier: License :: OSI Approved :: MIT License
Requires-Dist: requests (<2.22,>=2.21)
Requires-Dist: PyJWT (<1.8.0,>=1.7.1)
